syllagreek_utils/__init__.py
syllagreek_utils/preprocess.py
syllagreek_utils/syllabify.py
syllagreek_utils-0.1.0.dist-info/METADATA
syllagreek_utils-0.1.0.dist-info/WHEEL
syllagreek_utils-0.1.0.dist-info/top_level.txt
syllagreek_utils-0.1.0.dist-info/RECORD
